fastbook/__init__.py
fastbook/_nbdev.py
fastbook/images/cat.jpg
fastbook/images/grizzly.jpg
fastbook-0.0.29.dist-info/LICENSE
fastbook-0.0.29.dist-info/METADATA
fastbook-0.0.29.dist-info/WHEEL
fastbook-0.0.29.dist-info/top_level.txt
fastbook-0.0.29.dist-info/RECORD
