Metadata-Version: 2.1
Name: fastbook
Version: 0.0.29
Summary: Deep Learning for Coders, 2020
Home-page: https://github.com/fastai/fastbook
Author: Jeremy Howard and Sylvain Gugger
Author-email: info@fast.ai
License: Apache Software License 2.0
Keywords: python
Platform: UNKNOWN
Classifier: Development Status :: 5 - Production/Stable
Classifier: Intended Audience :: Developers
Classifier: License :: OSI Approved :: Apache Software License
Classifier: Natural Language :: English
Classifier: Programming Language :: Python :: 3.7
Classifier: Programming Language :: Python :: 3.8
Requires-Python: >=3.7
License-File: LICENSE
Requires-Dist: pip
Requires-Dist: packaging
Requires-Dist: fastai (>=2.6)
Requires-Dist: graphviz
Requires-Dist: pandas
Requires-Dist: requests
Requires-Dist: transformers
Requires-Dist: datasets
Requires-Dist: ipywidgets (<8)
Requires-Dist: sentencepiece
Provides-Extra: dev
